overleaf_mcp/__init__.py
overleaf_mcp/__main__.py
overleaf_mcp/mh_overleaf.py
overleaf-0.1.0.dist-info/METADATA
overleaf-0.1.0.dist-info/WHEEL
overleaf-0.1.0.dist-info/entry_points.txt
overleaf-0.1.0.dist-info/top_level.txt
overleaf-0.1.0.dist-info/RECORD
