Metadata-Version: 2.4
Name: overleaf
Version: 0.1.0
Summary: Add your description here
Requires-Python: >=3.10
Requires-Dist: mcp[cli]>=1.17.0
Requires-Dist: python-dotenv>=1.1.1
